procmux/__init__.py
procmux/args.py
procmux/config.py
procmux/log.py
procmux/main.py
procmux/server/__init__.py
procmux/server/client.py
procmux/server/server.py
procmux/tui/__init__.py
procmux/tui/app.py
procmux/tui/interpolation_dialog.py
procmux/tui/keybindings.py
procmux/tui/types.py
procmux/tui/controller/__init__.py
procmux/tui/controller/terminal_controller.py
procmux/tui/controller/tui_controller.py
procmux/tui/state/__init__.py
procmux/tui/state/process_state.py
procmux/tui/state/terminal_state.py
procmux/tui/state/tui_state.py
procmux/tui/view/__init__.py
procmux/tui/view/docs.py
procmux/tui/view/help.py
procmux/tui/view/process_description.py
procmux/tui/view/side_bar.py
procmux/tui/view/terminal.py
procmux/util/__init__.py
procmux/util/interpolation.py
procmux-2.0.3.dist-info/METADATA
procmux-2.0.3.dist-info/WHEEL
procmux-2.0.3.dist-info/entry_points.txt
procmux-2.0.3.dist-info/licenses/LICENSE.txt
procmux-2.0.3.dist-info/RECORD
