Metadata-Version: 2.4
Name: procmux
Version: 2.0.3
Summary: a TUI utility for running multiple commands in parallel in easily switchable terminals
Project-URL: homepage, https://github.com/napisani/procmux
Project-URL: repository, https://github.com/napisani/procmux
Project-URL: documentation, https://github.com/napisani/procmux
Author-email: Nick Pisani <napisani@yahoo.com>
License: MIT
License-File: LICENSE.txt
Classifier: License :: OSI Approved :: MIT License
Classifier: Programming Language :: Python :: 3
Classifier: Programming Language :: Python :: 3.8
Classifier: Programming Language :: Python :: 3.9
Classifier: Programming Language :: Python :: 3.10
Requires-Python: >=3.9.6
Requires-Dist: prompt-toolkit==2.0.10
Requires-Dist: ptterm==0.2
Requires-Dist: pyte==0.8.1
Requires-Dist: pytest==7.1.3
Requires-Dist: pyyaml==6.0.2
